{
  "updatedAt": "2026-06-18T01:40:52.346Z",
  "cacheUpdatedAt": "2026-06-18T01:40:52.346Z",
  "cacheSlotKey": "2026-06-17-1930",
  "waterWindowET": "19:30 ET",
  "maxAgeDays": 30,
  "states": [
    {
      "state": "AK",
      "sites": 55,
      "medianTempC": 8.9,
      "medianCond_uScm": 91,
      "medianPH": 7.85,
      "medianTDS_mgL": 61,
      "medianDO_mgL": 12.3,
      "medianTurb_NTU": null,
      "medianTurb_FNU": 122
    },
    {
      "state": "AL",
      "sites": 26,
      "medianTempC": 24.8,
      "medianCond_uScm": 312,
      "medianPH": 8,
      "medianTDS_mgL": 209,
      "medianDO_mgL": 7.5,
      "medianTurb_NTU": null,
      "medianTurb_FNU": 7.5
    },
    {
      "state": "AR",
      "sites": 30,
      "medianTempC": 25.3,
      "medianCond_uScm": 183,
      "medianPH": 6.9,
      "medianTDS_mgL": 122,
      "medianDO_mgL": 8.2,
      "medianTurb_NTU": null,
      "medianTurb_FNU": 8.5
    },
    {
      "state": "AZ",
      "sites": 17,
      "medianTempC": 22,
      "medianCond_uScm": 689,
      "medianPH": 8.3,
      "medianTDS_mgL": 462,
      "medianDO_mgL": 8.2,
      "medianTurb_NTU": null,
      "medianTurb_FNU": 1.6
    },
    {
      "state": "CA",
      "sites": 102,
      "medianTempC": 21.8,
      "medianCond_uScm": 354,
      "medianPH": 8,
      "medianTDS_mgL": 237,
      "medianDO_mgL": 8.6,
      "medianTurb_NTU": null,
      "medianTurb_FNU": 7.2
    },
    {
      "state": "CO",
      "sites": 114,
      "medianTempC": 19.4,
      "medianCond_uScm": 395,
      "medianPH": 8.4,
      "medianTDS_mgL": 265,
      "medianDO_mgL": 7.3,
      "medianTurb_NTU": null,
      "medianTurb_FNU": 4.8
    },
    {
      "state": "CT",
      "sites": 5,
      "medianTempC": 21.6,
      "medianCond_uScm": 152,
      "medianPH": 7.6,
      "medianTDS_mgL": 102,
      "medianDO_mgL": 8.3,
      "medianTurb_NTU": null,
      "medianTurb_FNU": 2.3
    },
    {
      "state": "DC",
      "sites": 4,
      "medianTempC": 25.8,
      "medianCond_uScm": 507,
      "medianPH": null,
      "medianTDS_mgL": 340,
      "medianDO_mgL": null,
      "medianTurb_NTU": null,
      "medianTurb_FNU": null
    },
    {
      "state": "DE",
      "sites": 16,
      "medianTempC": 24.5,
      "medianCond_uScm": 336,
      "medianPH": 7.1,
      "medianTDS_mgL": 225,
      "medianDO_mgL": 5.6,
      "medianTurb_NTU": null,
      "medianTurb_FNU": null
    },
    {
      "state": "FL",
      "sites": 93,
      "medianTempC": 30.3,
      "medianCond_uScm": 1180,
      "medianPH": null,
      "medianTDS_mgL": 791,
      "medianDO_mgL": 6,
      "medianTurb_NTU": null,
      "medianTurb_FNU": null
    },
    {
      "state": "GA",
      "sites": 97,
      "medianTempC": 24.2,
      "medianCond_uScm": 95,
      "medianPH": 7,
      "medianTDS_mgL": 64,
      "medianDO_mgL": 6.9,
      "medianTurb_NTU": null,
      "medianTurb_FNU": 8.6
    },
    {
      "state": "HI",
      "sites": 5,
      "medianTempC": null,
      "medianCond_uScm": null,
      "medianPH": null,
      "medianTDS_mgL": null,
      "medianDO_mgL": null,
      "medianTurb_NTU": null,
      "medianTurb_FNU": 7
    },
    {
      "state": "IA",
      "sites": 9,
      "medianTempC": 22,
      "medianCond_uScm": null,
      "medianPH": null,
      "medianTDS_mgL": null,
      "medianDO_mgL": null,
      "medianTurb_NTU": null,
      "medianTurb_FNU": null
    },
    {
      "state": "ID",
      "sites": 29,
      "medianTempC": 15.5,
      "medianCond_uScm": 63,
      "medianPH": null,
      "medianTDS_mgL": 43,
      "medianDO_mgL": null,
      "medianTurb_NTU": null,
      "medianTurb_FNU": 2.8
    },
    {
      "state": "IL",
      "sites": 24,
      "medianTempC": 20.5,
      "medianCond_uScm": 616,
      "medianPH": 8,
      "medianTDS_mgL": 413,
      "medianDO_mgL": 6.8,
      "medianTurb_NTU": null,
      "medianTurb_FNU": 21.8
    },
    {
      "state": "IN",
      "sites": 36,
      "medianTempC": 18.8,
      "medianCond_uScm": 610,
      "medianPH": 7.9,
      "medianTDS_mgL": 409,
      "medianDO_mgL": 7.4,
      "medianTurb_NTU": null,
      "medianTurb_FNU": 13.2
    },
    {
      "state": "KS",
      "sites": 22,
      "medianTempC": 26.6,
      "medianCond_uScm": 443,
      "medianPH": 8,
      "medianTDS_mgL": 297,
      "medianDO_mgL": 6.7,
      "medianTurb_NTU": null,
      "medianTurb_FNU": 135.5
    },
    {
      "state": "KY",
      "sites": 42,
      "medianTempC": 22.4,
      "medianCond_uScm": 625,
      "medianPH": 8,
      "medianTDS_mgL": 418,
      "medianDO_mgL": 7.6,
      "medianTurb_NTU": null,
      "medianTurb_FNU": 2.7
    },
    {
      "state": "LA",
      "sites": 15,
      "medianTempC": 28.3,
      "medianCond_uScm": 405,
      "medianPH": null,
      "medianTDS_mgL": 271,
      "medianDO_mgL": 5.7,
      "medianTurb_NTU": null,
      "medianTurb_FNU": 60.8
    },
    {
      "state": "MA",
      "sites": 17,
      "medianTempC": 19.3,
      "medianCond_uScm": 756,
      "medianPH": null,
      "medianTDS_mgL": 507,
      "medianDO_mgL": null,
      "medianTurb_NTU": null,
      "medianTurb_FNU": null
    },
    {
      "state": "MD",
      "sites": 17,
      "medianTempC": 22.3,
      "medianCond_uScm": 430,
      "medianPH": 7.65,
      "medianTDS_mgL": 288,
      "medianDO_mgL": 6.8,
      "medianTurb_NTU": null,
      "medianTurb_FNU": 4.9
    },
    {
      "state": "ME",
      "sites": 4,
      "medianTempC": 21.6,
      "medianCond_uScm": null,
      "medianPH": null,
      "medianTDS_mgL": null,
      "medianDO_mgL": null,
      "medianTurb_NTU": null,
      "medianTurb_FNU": null
    },
    {
      "state": "MI",
      "sites": 51,
      "medianTempC": 17.1,
      "medianCond_uScm": 628,
      "medianPH": null,
      "medianTDS_mgL": 421,
      "medianDO_mgL": 8.1,
      "medianTurb_NTU": null,
      "medianTurb_FNU": 17.5
    },
    {
      "state": "MN",
      "sites": 10,
      "medianTempC": 18.9,
      "medianCond_uScm": 571,
      "medianPH": null,
      "medianTDS_mgL": 383,
      "medianDO_mgL": null,
      "medianTurb_NTU": null,
      "medianTurb_FNU": null
    },
    {
      "state": "MO",
      "sites": 23,
      "medianTempC": 25.3,
      "medianCond_uScm": 413,
      "medianPH": 7.8,
      "medianTDS_mgL": 277,
      "medianDO_mgL": 6.8,
      "medianTurb_NTU": null,
      "medianTurb_FNU": 71.8
    },
    {
      "state": "MS",
      "sites": 3,
      "medianTempC": 25.3,
      "medianCond_uScm": null,
      "medianPH": null,
      "medianTDS_mgL": null,
      "medianDO_mgL": null,
      "medianTurb_NTU": null,
      "medianTurb_FNU": null
    },
    {
      "state": "MT",
      "sites": 74,
      "medianTempC": 17.1,
      "medianCond_uScm": 400,
      "medianPH": 8.3,
      "medianTDS_mgL": 268,
      "medianDO_mgL": 9.3,
      "medianTurb_NTU": null,
      "medianTurb_FNU": 2.1
    },
    {
      "state": "NC",
      "sites": 30,
      "medianTempC": 24.6,
      "medianCond_uScm": 81,
      "medianPH": 7.5,
      "medianTDS_mgL": 54,
      "medianDO_mgL": 7.4,
      "medianTurb_NTU": null,
      "medianTurb_FNU": 7.4
    },
    {
      "state": "ND",
      "sites": 16,
      "medianTempC": 19.3,
      "medianCond_uScm": 1810,
      "medianPH": 8.4,
      "medianTDS_mgL": 1213,
      "medianDO_mgL": 7.6,
      "medianTurb_NTU": null,
      "medianTurb_FNU": 66.6
    },
    {
      "state": "NE",
      "sites": 12,
      "medianTempC": 25.5,
      "medianCond_uScm": 413,
      "medianPH": 8.65,
      "medianTDS_mgL": 277,
      "medianDO_mgL": 9.5,
      "medianTurb_NTU": null,
      "medianTurb_FNU": 43.8
    },
    {
      "state": "NH",
      "sites": 9,
      "medianTempC": 20.8,
      "medianCond_uScm": null,
      "medianPH": null,
      "medianTDS_mgL": null,
      "medianDO_mgL": null,
      "medianTurb_NTU": null,
      "medianTurb_FNU": null
    },
    {
      "state": "NJ",
      "sites": 38,
      "medianTempC": 23.9,
      "medianCond_uScm": 267,
      "medianPH": 8.4,
      "medianTDS_mgL": 179,
      "medianDO_mgL": 8.6,
      "medianTurb_NTU": null,
      "medianTurb_FNU": 4.8
    },
    {
      "state": "NM",
      "sites": 18,
      "medianTempC": 24.8,
      "medianCond_uScm": 868,
      "medianPH": null,
      "medianTDS_mgL": 581,
      "medianDO_mgL": 6.1,
      "medianTurb_NTU": null,
      "medianTurb_FNU": 8.3
    },
    {
      "state": "NV",
      "sites": 15,
      "medianTempC": 24.4,
      "medianCond_uScm": 248,
      "medianPH": null,
      "medianTDS_mgL": 167,
      "medianDO_mgL": 7.6,
      "medianTurb_NTU": null,
      "medianTurb_FNU": null
    },
    {
      "state": "NY",
      "sites": 78,
      "medianTempC": 20,
      "medianCond_uScm": 341,
      "medianPH": 7.85,
      "medianTDS_mgL": 228,
      "medianDO_mgL": 8,
      "medianTurb_NTU": null,
      "medianTurb_FNU": 3
    },
    {
      "state": "OH",
      "sites": 53,
      "medianTempC": 20.9,
      "medianCond_uScm": 512,
      "medianPH": 8,
      "medianTDS_mgL": 343,
      "medianDO_mgL": 7.4,
      "medianTurb_NTU": null,
      "medianTurb_FNU": 8.7
    },
    {
      "state": "OK",
      "sites": 19,
      "medianTempC": 28.5,
      "medianCond_uScm": 1065,
      "medianPH": 7.4,
      "medianTDS_mgL": 714,
      "medianDO_mgL": 8,
      "medianTurb_NTU": null,
      "medianTurb_FNU": 0.5
    },
    {
      "state": "OR",
      "sites": 220,
      "medianTempC": 19.1,
      "medianCond_uScm": 67,
      "medianPH": 7.8,
      "medianTDS_mgL": 45,
      "medianDO_mgL": 9.4,
      "medianTurb_NTU": null,
      "medianTurb_FNU": 1.4
    },
    {
      "state": "PA",
      "sites": 135,
      "medianTempC": 21.7,
      "medianCond_uScm": 382,
      "medianPH": 7.8,
      "medianTDS_mgL": 256,
      "medianDO_mgL": 8.4,
      "medianTurb_NTU": null,
      "medianTurb_FNU": 3.9
    },
    {
      "state": "PR",
      "sites": 3,
      "medianTempC": 27.9,
      "medianCond_uScm": null,
      "medianPH": null,
      "medianTDS_mgL": null,
      "medianDO_mgL": null,
      "medianTurb_NTU": null,
      "medianTurb_FNU": null
    },
    {
      "state": "RI",
      "sites": 14,
      "medianTempC": 19,
      "medianCond_uScm": 164,
      "medianPH": null,
      "medianTDS_mgL": 110,
      "medianDO_mgL": null,
      "medianTurb_NTU": null,
      "medianTurb_FNU": null
    },
    {
      "state": "SC",
      "sites": 65,
      "medianTempC": 28.1,
      "medianCond_uScm": 425,
      "medianPH": 7.35,
      "medianTDS_mgL": 285,
      "medianDO_mgL": 5.5,
      "medianTurb_NTU": null,
      "medianTurb_FNU": 4.6
    },
    {
      "state": "SD",
      "sites": 1,
      "medianTempC": null,
      "medianCond_uScm": null,
      "medianPH": null,
      "medianTDS_mgL": null,
      "medianDO_mgL": null,
      "medianTurb_NTU": null,
      "medianTurb_FNU": null
    },
    {
      "state": "TN",
      "sites": 22,
      "medianTempC": 25.2,
      "medianCond_uScm": 301,
      "medianPH": 7.9,
      "medianTDS_mgL": 201,
      "medianDO_mgL": 7.8,
      "medianTurb_NTU": null,
      "medianTurb_FNU": 11.6
    },
    {
      "state": "TX",
      "sites": 60,
      "medianTempC": 29,
      "medianCond_uScm": 503,
      "medianPH": 7.8,
      "medianTDS_mgL": 337,
      "medianDO_mgL": 6.6,
      "medianTurb_NTU": null,
      "medianTurb_FNU": 95
    },
    {
      "state": "UT",
      "sites": 23,
      "medianTempC": 23.7,
      "medianCond_uScm": 840,
      "medianPH": 8.7,
      "medianTDS_mgL": 563,
      "medianDO_mgL": 7.6,
      "medianTurb_NTU": null,
      "medianTurb_FNU": 11.7
    },
    {
      "state": "VA",
      "sites": 46,
      "medianTempC": 22.9,
      "medianCond_uScm": 231,
      "medianPH": 7.35,
      "medianTDS_mgL": 155,
      "medianDO_mgL": 7.3,
      "medianTurb_NTU": null,
      "medianTurb_FNU": 3
    },
    {
      "state": "VT",
      "sites": 2,
      "medianTempC": null,
      "medianCond_uScm": null,
      "medianPH": null,
      "medianTDS_mgL": null,
      "medianDO_mgL": null,
      "medianTurb_NTU": null,
      "medianTurb_FNU": null
    },
    {
      "state": "WA",
      "sites": 86,
      "medianTempC": 15,
      "medianCond_uScm": 124,
      "medianPH": 7.65,
      "medianTDS_mgL": 83,
      "medianDO_mgL": 9.8,
      "medianTurb_NTU": null,
      "medianTurb_FNU": 2.1
    },
    {
      "state": "WI",
      "sites": 32,
      "medianTempC": 17.4,
      "medianCond_uScm": 490,
      "medianPH": 7.95,
      "medianTDS_mgL": 328,
      "medianDO_mgL": 7.9,
      "medianTurb_NTU": null,
      "medianTurb_FNU": 16.1
    },
    {
      "state": "WV",
      "sites": 35,
      "medianTempC": 21.8,
      "medianCond_uScm": 143,
      "medianPH": 7.75,
      "medianTDS_mgL": 96,
      "medianDO_mgL": 8.7,
      "medianTurb_NTU": null,
      "medianTurb_FNU": 2.4
    },
    {
      "state": "WY",
      "sites": 29,
      "medianTempC": 16.1,
      "medianCond_uScm": 336,
      "medianPH": 8.1,
      "medianTDS_mgL": 225,
      "medianDO_mgL": 8.1,
      "medianTurb_NTU": null,
      "medianTurb_FNU": null
    }
  ]
}