{
  "updatedAt": "2026-07-05T23:36:14.812Z",
  "cacheUpdatedAt": "2026-07-05T23:36:14.812Z",
  "cacheSlotKey": "2026-07-05-1930",
  "waterWindowET": "19:30 ET",
  "maxAgeDays": 30,
  "states": [
    {
      "state": "AK",
      "sites": 59,
      "medianTempC": 9,
      "medianCond_uScm": 86,
      "medianPH": 7.6,
      "medianTDS_mgL": 58,
      "medianDO_mgL": 12.3,
      "medianTurb_NTU": null,
      "medianTurb_FNU": 25.3
    },
    {
      "state": "AL",
      "sites": 27,
      "medianTempC": 28,
      "medianCond_uScm": 325,
      "medianPH": 8.15,
      "medianTDS_mgL": 218,
      "medianDO_mgL": 7.8,
      "medianTurb_NTU": null,
      "medianTurb_FNU": 7.1
    },
    {
      "state": "AR",
      "sites": 30,
      "medianTempC": 27,
      "medianCond_uScm": 224,
      "medianPH": 6.8,
      "medianTDS_mgL": 150,
      "medianDO_mgL": 7.3,
      "medianTurb_NTU": null,
      "medianTurb_FNU": 16.9
    },
    {
      "state": "AZ",
      "sites": 16,
      "medianTempC": 21.6,
      "medianCond_uScm": 1092,
      "medianPH": 8.4,
      "medianTDS_mgL": 731,
      "medianDO_mgL": 8.1,
      "medianTurb_NTU": null,
      "medianTurb_FNU": 0.8
    },
    {
      "state": "CA",
      "sites": 102,
      "medianTempC": 21.5,
      "medianCond_uScm": 386,
      "medianPH": 8.2,
      "medianTDS_mgL": 259,
      "medianDO_mgL": 9.6,
      "medianTurb_NTU": null,
      "medianTurb_FNU": 5.4
    },
    {
      "state": "CO",
      "sites": 113,
      "medianTempC": 20.8,
      "medianCond_uScm": 389,
      "medianPH": 8.6,
      "medianTDS_mgL": 261,
      "medianDO_mgL": 8.4,
      "medianTurb_NTU": null,
      "medianTurb_FNU": 4.9
    },
    {
      "state": "CT",
      "sites": 5,
      "medianTempC": 25.2,
      "medianCond_uScm": 149,
      "medianPH": 7.5,
      "medianTDS_mgL": 100,
      "medianDO_mgL": 7.9,
      "medianTurb_NTU": null,
      "medianTurb_FNU": 3.2
    },
    {
      "state": "DC",
      "sites": 4,
      "medianTempC": 30.7,
      "medianCond_uScm": 478,
      "medianPH": null,
      "medianTDS_mgL": 321,
      "medianDO_mgL": null,
      "medianTurb_NTU": null,
      "medianTurb_FNU": null
    },
    {
      "state": "DE",
      "sites": 17,
      "medianTempC": 29,
      "medianCond_uScm": 403,
      "medianPH": 7.25,
      "medianTDS_mgL": 270,
      "medianDO_mgL": 4.2,
      "medianTurb_NTU": null,
      "medianTurb_FNU": null
    },
    {
      "state": "FL",
      "sites": 93,
      "medianTempC": 31.1,
      "medianCond_uScm": 1100,
      "medianPH": null,
      "medianTDS_mgL": 737,
      "medianDO_mgL": 5.1,
      "medianTurb_NTU": null,
      "medianTurb_FNU": null
    },
    {
      "state": "GA",
      "sites": 97,
      "medianTempC": 26.3,
      "medianCond_uScm": 92,
      "medianPH": 7,
      "medianTDS_mgL": 62,
      "medianDO_mgL": 6.5,
      "medianTurb_NTU": null,
      "medianTurb_FNU": 12
    },
    {
      "state": "HI",
      "sites": 5,
      "medianTempC": null,
      "medianCond_uScm": null,
      "medianPH": null,
      "medianTDS_mgL": null,
      "medianDO_mgL": null,
      "medianTurb_NTU": null,
      "medianTurb_FNU": 8.5
    },
    {
      "state": "IA",
      "sites": 11,
      "medianTempC": 27.6,
      "medianCond_uScm": null,
      "medianPH": null,
      "medianTDS_mgL": null,
      "medianDO_mgL": null,
      "medianTurb_NTU": null,
      "medianTurb_FNU": null
    },
    {
      "state": "ID",
      "sites": 30,
      "medianTempC": 17.1,
      "medianCond_uScm": 63,
      "medianPH": null,
      "medianTDS_mgL": 42,
      "medianDO_mgL": null,
      "medianTurb_NTU": null,
      "medianTurb_FNU": 3.1
    },
    {
      "state": "IL",
      "sites": 24,
      "medianTempC": 26.3,
      "medianCond_uScm": 558,
      "medianPH": 7.8,
      "medianTDS_mgL": 374,
      "medianDO_mgL": 6.4,
      "medianTurb_NTU": null,
      "medianTurb_FNU": 29
    },
    {
      "state": "IN",
      "sites": 36,
      "medianTempC": 24.3,
      "medianCond_uScm": 590,
      "medianPH": 7.8,
      "medianTDS_mgL": 395,
      "medianDO_mgL": 7.4,
      "medianTurb_NTU": null,
      "medianTurb_FNU": 17.9
    },
    {
      "state": "KS",
      "sites": 24,
      "medianTempC": 27.4,
      "medianCond_uScm": 526,
      "medianPH": 8.1,
      "medianTDS_mgL": 352,
      "medianDO_mgL": 8.6,
      "medianTurb_NTU": null,
      "medianTurb_FNU": 39.9
    },
    {
      "state": "KY",
      "sites": 43,
      "medianTempC": 25.8,
      "medianCond_uScm": 565,
      "medianPH": 8,
      "medianTDS_mgL": 379,
      "medianDO_mgL": 7.4,
      "medianTurb_NTU": null,
      "medianTurb_FNU": 10
    },
    {
      "state": "LA",
      "sites": 13,
      "medianTempC": 30.1,
      "medianCond_uScm": 405,
      "medianPH": null,
      "medianTDS_mgL": 272,
      "medianDO_mgL": 5.1,
      "medianTurb_NTU": null,
      "medianTurb_FNU": 85.8
    },
    {
      "state": "MA",
      "sites": 17,
      "medianTempC": 24,
      "medianCond_uScm": 944,
      "medianPH": null,
      "medianTDS_mgL": 633,
      "medianDO_mgL": null,
      "medianTurb_NTU": null,
      "medianTurb_FNU": null
    },
    {
      "state": "MD",
      "sites": 16,
      "medianTempC": 28,
      "medianCond_uScm": 429,
      "medianPH": 7.7,
      "medianTDS_mgL": 288,
      "medianDO_mgL": 7.5,
      "medianTurb_NTU": null,
      "medianTurb_FNU": 4
    },
    {
      "state": "ME",
      "sites": 4,
      "medianTempC": 24.6,
      "medianCond_uScm": null,
      "medianPH": null,
      "medianTDS_mgL": null,
      "medianDO_mgL": null,
      "medianTurb_NTU": null,
      "medianTurb_FNU": null
    },
    {
      "state": "MI",
      "sites": 52,
      "medianTempC": 22.6,
      "medianCond_uScm": 628,
      "medianPH": null,
      "medianTDS_mgL": 421,
      "medianDO_mgL": 8.1,
      "medianTurb_NTU": null,
      "medianTurb_FNU": 49
    },
    {
      "state": "MN",
      "sites": 8,
      "medianTempC": 26.6,
      "medianCond_uScm": 501,
      "medianPH": null,
      "medianTDS_mgL": 336,
      "medianDO_mgL": null,
      "medianTurb_NTU": null,
      "medianTurb_FNU": null
    },
    {
      "state": "MO",
      "sites": 23,
      "medianTempC": 28.2,
      "medianCond_uScm": 502,
      "medianPH": 8.1,
      "medianTDS_mgL": 337,
      "medianDO_mgL": 6.5,
      "medianTurb_NTU": null,
      "medianTurb_FNU": 31.3
    },
    {
      "state": "MS",
      "sites": 4,
      "medianTempC": 29.8,
      "medianCond_uScm": null,
      "medianPH": null,
      "medianTDS_mgL": null,
      "medianDO_mgL": null,
      "medianTurb_NTU": null,
      "medianTurb_FNU": null
    },
    {
      "state": "MT",
      "sites": 76,
      "medianTempC": 19.3,
      "medianCond_uScm": 368,
      "medianPH": 8.1,
      "medianTDS_mgL": 247,
      "medianDO_mgL": 8.1,
      "medianTurb_NTU": null,
      "medianTurb_FNU": 2.8
    },
    {
      "state": "NC",
      "sites": 30,
      "medianTempC": 26.8,
      "medianCond_uScm": 113,
      "medianPH": 7.6,
      "medianTDS_mgL": 76,
      "medianDO_mgL": 6.6,
      "medianTurb_NTU": null,
      "medianTurb_FNU": 5.9
    },
    {
      "state": "ND",
      "sites": 17,
      "medianTempC": 27.1,
      "medianCond_uScm": 1195,
      "medianPH": 8.55,
      "medianTDS_mgL": 801,
      "medianDO_mgL": 9,
      "medianTurb_NTU": null,
      "medianTurb_FNU": 39.8
    },
    {
      "state": "NE",
      "sites": 12,
      "medianTempC": 30.9,
      "medianCond_uScm": 480,
      "medianPH": 8.6,
      "medianTDS_mgL": 322,
      "medianDO_mgL": 8.1,
      "medianTurb_NTU": null,
      "medianTurb_FNU": 74.9
    },
    {
      "state": "NH",
      "sites": 9,
      "medianTempC": 25.7,
      "medianCond_uScm": null,
      "medianPH": null,
      "medianTDS_mgL": null,
      "medianDO_mgL": null,
      "medianTurb_NTU": null,
      "medianTurb_FNU": null
    },
    {
      "state": "NJ",
      "sites": 34,
      "medianTempC": 28.6,
      "medianCond_uScm": 270,
      "medianPH": 8.6,
      "medianTDS_mgL": 181,
      "medianDO_mgL": 9.1,
      "medianTurb_NTU": null,
      "medianTurb_FNU": 3
    },
    {
      "state": "NM",
      "sites": 19,
      "medianTempC": 23.6,
      "medianCond_uScm": 740,
      "medianPH": null,
      "medianTDS_mgL": 496,
      "medianDO_mgL": 7.3,
      "medianTurb_NTU": null,
      "medianTurb_FNU": 16
    },
    {
      "state": "NV",
      "sites": 15,
      "medianTempC": 21.8,
      "medianCond_uScm": 309,
      "medianPH": null,
      "medianTDS_mgL": 207,
      "medianDO_mgL": 8.1,
      "medianTurb_NTU": null,
      "medianTurb_FNU": null
    },
    {
      "state": "NY",
      "sites": 80,
      "medianTempC": 24.7,
      "medianCond_uScm": 354,
      "medianPH": 7.2,
      "medianTDS_mgL": 237,
      "medianDO_mgL": 8.1,
      "medianTurb_NTU": null,
      "medianTurb_FNU": 2.3
    },
    {
      "state": "OH",
      "sites": 53,
      "medianTempC": 25.3,
      "medianCond_uScm": 491,
      "medianPH": 8.2,
      "medianTDS_mgL": 329,
      "medianDO_mgL": 8.2,
      "medianTurb_NTU": null,
      "medianTurb_FNU": 10.7
    },
    {
      "state": "OK",
      "sites": 18,
      "medianTempC": 28.1,
      "medianCond_uScm": 744,
      "medianPH": null,
      "medianTDS_mgL": 498,
      "medianDO_mgL": 6.4,
      "medianTurb_NTU": null,
      "medianTurb_FNU": 0.5
    },
    {
      "state": "OR",
      "sites": 225,
      "medianTempC": 19.3,
      "medianCond_uScm": 69,
      "medianPH": 7.9,
      "medianTDS_mgL": 47,
      "medianDO_mgL": 9.6,
      "medianTurb_NTU": null,
      "medianTurb_FNU": 1.6
    },
    {
      "state": "PA",
      "sites": 135,
      "medianTempC": 26.2,
      "medianCond_uScm": 388,
      "medianPH": 7.8,
      "medianTDS_mgL": 260,
      "medianDO_mgL": 7.8,
      "medianTurb_NTU": null,
      "medianTurb_FNU": 4.8
    },
    {
      "state": "PR",
      "sites": 3,
      "medianTempC": 28.4,
      "medianCond_uScm": null,
      "medianPH": null,
      "medianTDS_mgL": null,
      "medianDO_mgL": null,
      "medianTurb_NTU": null,
      "medianTurb_FNU": null
    },
    {
      "state": "RI",
      "sites": 14,
      "medianTempC": 24.1,
      "medianCond_uScm": 168,
      "medianPH": null,
      "medianTDS_mgL": 113,
      "medianDO_mgL": null,
      "medianTurb_NTU": null,
      "medianTurb_FNU": null
    },
    {
      "state": "SC",
      "sites": 65,
      "medianTempC": 30.6,
      "medianCond_uScm": 649,
      "medianPH": 7.45,
      "medianTDS_mgL": 435,
      "medianDO_mgL": 6,
      "medianTurb_NTU": null,
      "medianTurb_FNU": 5.3
    },
    {
      "state": "SD",
      "sites": 1,
      "medianTempC": null,
      "medianCond_uScm": null,
      "medianPH": null,
      "medianTDS_mgL": null,
      "medianDO_mgL": null,
      "medianTurb_NTU": null,
      "medianTurb_FNU": null
    },
    {
      "state": "TN",
      "sites": 21,
      "medianTempC": 25.4,
      "medianCond_uScm": 270,
      "medianPH": 7.7,
      "medianTDS_mgL": 181,
      "medianDO_mgL": 6.9,
      "medianTurb_NTU": null,
      "medianTurb_FNU": 8.7
    },
    {
      "state": "TX",
      "sites": 57,
      "medianTempC": 31.7,
      "medianCond_uScm": 779,
      "medianPH": 7.95,
      "medianTDS_mgL": 522,
      "medianDO_mgL": 7.8,
      "medianTurb_NTU": null,
      "medianTurb_FNU": 19.9
    },
    {
      "state": "UT",
      "sites": 23,
      "medianTempC": 23.6,
      "medianCond_uScm": 922,
      "medianPH": 8.5,
      "medianTDS_mgL": 618,
      "medianDO_mgL": 8.3,
      "medianTurb_NTU": null,
      "medianTurb_FNU": 2
    },
    {
      "state": "VA",
      "sites": 46,
      "medianTempC": 26.8,
      "medianCond_uScm": 291,
      "medianPH": 7.4,
      "medianTDS_mgL": 195,
      "medianDO_mgL": 7.1,
      "medianTurb_NTU": null,
      "medianTurb_FNU": 4.3
    },
    {
      "state": "VT",
      "sites": 2,
      "medianTempC": null,
      "medianCond_uScm": null,
      "medianPH": null,
      "medianTDS_mgL": null,
      "medianDO_mgL": null,
      "medianTurb_NTU": null,
      "medianTurb_FNU": null
    },
    {
      "state": "WA",
      "sites": 86,
      "medianTempC": 16.7,
      "medianCond_uScm": 144,
      "medianPH": 7.9,
      "medianTDS_mgL": 96,
      "medianDO_mgL": 10,
      "medianTurb_NTU": null,
      "medianTurb_FNU": 1.6
    },
    {
      "state": "WI",
      "sites": 31,
      "medianTempC": 23.7,
      "medianCond_uScm": 706,
      "medianPH": 8.15,
      "medianTDS_mgL": 473,
      "medianDO_mgL": 8.4,
      "medianTurb_NTU": null,
      "medianTurb_FNU": 12.3
    },
    {
      "state": "WV",
      "sites": 35,
      "medianTempC": 26.6,
      "medianCond_uScm": 185,
      "medianPH": 7.95,
      "medianTDS_mgL": 124,
      "medianDO_mgL": 8.1,
      "medianTurb_NTU": null,
      "medianTurb_FNU": 3
    },
    {
      "state": "WY",
      "sites": 29,
      "medianTempC": 17.6,
      "medianCond_uScm": 322,
      "medianPH": 8.4,
      "medianTDS_mgL": 216,
      "medianDO_mgL": 8.3,
      "medianTurb_NTU": null,
      "medianTurb_FNU": null
    }
  ]
}